<?xml version="1.0" encoding="UTF-8"?>
<beans xmlns="http://www.springframework.org/schema/beans"
	xmlns:xsi="http://www.w3.org/2001/XMLSchema-instance"
	xmlns:mybatis-spring="http://mybatis.org/schema/mybatis-spring"
	xsi:schemaLocation="http://www.springframework.org/schema/beans https://www.springframework.org/schema/beans/spring-beans.xsd
						http://mybatis.org/schema/mybatis-spring http://mybatis.org/schema/mybatis-spring-1.2.xsd">
	
	<!-- Root Context: defines shared resources visible to all other web components -->
	<!-- DriverManagerDataSource 빈 등록 -->
	<bean id="dataSource" class="org.springframework.jdbc.datasource.DriverManagerDataSource">
		<property name="driverClassName" value="com.mysql.jdbc.Driver"></property>
		<property name="url" value="jdbc:mysql://127.0.0.1:3306/joeun"></property>
		<property name="username" value="joeun"></property>
		<property name="password" value="123456"></property>
	</bean>	
	
	<!-- SqlSessionFactoryBean 빈 등록 -->
	<bean id="sqlSessionFactory" class="org.mybatis.spring.SqlSessionFactoryBean">
		<property name="dataSource" ref="dataSource" />
<!-- 		<property name="configLocation" value="classpath:/mybatis-config.xml"></property> -->
	</bean>
	
	<!-- MyBatis SqlSessionTemplate 빈 등록 -->
	<bean id="sqlSession" class="org.mybatis.spring.SqlSessionTemplate" destroy-method="clearCache">
	 <constructor-arg name="sqlSessionFactory" ref="sqlSessionFactory"></constructor-arg>
	</bean>
	
	<!-- Mapper 인터페이스 패키지 경로 설정 -->
	<mybatis-spring:scan base-package="com.joeun.test.mapper" />

	
		
</beans>
